LICENSE
MANIFEST.in
README.md
setup.cfg
setup.py
tmpo.ipynb
tmpo/__init__.py
tmpo.egg-info/PKG-INFO
tmpo.egg-info/SOURCES.txt
tmpo.egg-info/dependency_links.txt
tmpo.egg-info/requires.txt
tmpo.egg-info/top_level.txt