Metadata-Version: 1.1
Name: tmpo
Version: 0.2.10
Summary: A python client for the tmpo protocol for timeseries
Home-page: https://github.com/flukso/tmpo-py
Author: Bart Van Der Meerssche
Author-email: bart@flukso.net
License: MIT
Keywords: data monitoring tmpo timeseries sqlite
Platform: UNKNOWN
Classifier: Development Status :: 4 - Beta
Classifier: Intended Audience :: Developers
Classifier: Topic :: Scientific/Engineering
Classifier: License :: OSI Approved :: MIT License
Classifier: Programming Language :: Python :: 2
Classifier: Programming Language :: Python :: 2.6
Classifier: Programming Language :: Python :: 2.7
Classifier: Programming Language :: Python :: 3
Classifier: Programming Language :: Python :: 3.2
Classifier: Programming Language :: Python :: 3.3
Classifier: Programming Language :: Python :: 3.4
